QARealtimeCollector/__init__.py
QARealtimeCollector/management.py
QARealtimeCollector/setting.py
QARealtimeCollector/util.py
QARealtimeCollector/webserver.py
QARealtimeCollector/clients/__init__.py
QARealtimeCollector/clients/subscribe_clients.py
QARealtimeCollector/clients/test.py
QARealtimeCollector/collectors/__init__.py
QARealtimeCollector/collectors/crawlercollector.py
QARealtimeCollector/collectors/ctpbeecollector.py
QARealtimeCollector/collectors/ctpbeecollector_second.py
QARealtimeCollector/collectors/simcollector.py
QARealtimeCollector/collectors/simmarket.py
QARealtimeCollector/collectors/stockbarcollector.py
QARealtimeCollector/collectors/stockcollector.py
QARealtimeCollector/collectors/wscollector.py
QARealtimeCollector/datahandler/__init__.py
QARealtimeCollector/datahandler/realtime_resampler.py
QARealtimeCollector/datahandler/stock_resampler.py
qarealtime_collector-0.0.10.dist-info/LICENSE
qarealtime_collector-0.0.10.dist-info/METADATA
qarealtime_collector-0.0.10.dist-info/WHEEL
qarealtime_collector-0.0.10.dist-info/entry_points.txt
qarealtime_collector-0.0.10.dist-info/top_level.txt
qarealtime_collector-0.0.10.dist-info/zip-safe
qarealtime_collector-0.0.10.dist-info/RECORD
