Metadata-Version: 2.1
Name: qarealtime-collector
Version: 0.0.10
Summary: QARealtimeCollector: QUANTAXIS REALTIME MARKETDATA COLLECTORS
Home-page: https://github.com/yutiansut/QUANTAXIS_RealtimeCollector
Author: yutiansut
Author-email: yutiansut@qq.com
License: MIT
Keywords: quantaxis,quant,finance,Backtest,Framework
Platform: UNKNOWN
Classifier: License :: OSI Approved :: MIT License
Classifier: Programming Language :: Python
Classifier: Intended Audience :: Developers
Classifier: Operating System :: OS Independent
Requires-Dist: quantaxis
Requires-Dist: quantaxis-pubsub
Requires-Dist: quantaxis-otgbroker
Requires-Dist: quantaxis-randomprice
Requires-Dist: quantaxis-webserver
